pysilentwave/__init__.py
pysilentwave/client.py
pysilentwave/exceptions.py
pysilentwave-0.1.3.dist-info/licenses/LICENSE
pysilentwave-0.1.3.dist-info/METADATA
pysilentwave-0.1.3.dist-info/WHEEL
pysilentwave-0.1.3.dist-info/top_level.txt
pysilentwave-0.1.3.dist-info/RECORD
