Metadata-Version: 2.4
Name: pysilentwave
Version: 0.1.3
Summary: API client for TheSilentWave devices
Home-page: https://github.com/thesilentwave/pysilentwave
Author: TheSilentWave
Author-email: TheSilentWave <mail@thesilentwave.de>
License: MIT
Project-URL: Homepage, https://github.com/thesilentwave/pysilentwave
Classifier: Development Status :: 3 - Alpha
Classifier: Intended Audience :: Developers
Classifier: License :: OSI Approved :: MIT License
Classifier: Programming Language :: Python :: 3
Classifier: Programming Language :: Python :: 3.9
Classifier: Programming Language :: Python :: 3.10
Classifier: Programming Language :: Python :: 3.11
Requires-Python: >=3.9
License-File: LICENSE
Requires-Dist: aiohttp>=3.8.0
Dynamic: author
Dynamic: home-page
Dynamic: license-file
Dynamic: requires-python
